matplotlib_radar/__init__.py
matplotlib_radar/_radar_chart.py
matplotlib_radar/_version.py
matplotlib_radar-0.2.0.dist-info/licenses/LICENSE
matplotlib_radar-0.2.0.dist-info/WHEEL
matplotlib_radar-0.2.0.dist-info/METADATA
matplotlib_radar-0.2.0.dist-info/RECORD
