Metadata-Version: 2.4
Name: matplotlib-radar
Version: 0.2.0
Summary: Radar chart for matplotlib
Author: harryhaller001
Maintainer-email: harryhaller001 <harryhaller001@gmail.com>
Requires-Python: >=3.11
Classifier: Development Status :: 3 - Alpha
Classifier: Framework :: Matplotlib
Classifier: Intended Audience :: Science/Research
Classifier: License :: OSI Approved :: MIT License
Classifier: Natural Language :: English
Classifier: Operating System :: OS Independent
Classifier: Programming Language :: Python :: 3 :: Only
Classifier: Programming Language :: Python :: 3.11
Classifier: Programming Language :: Python :: 3.12
Classifier: Programming Language :: Python :: 3.13
Classifier: Programming Language :: Python :: 3.14
Classifier: Typing :: Typed
License-File: LICENSE
Requires-Dist: matplotlib
Requires-Dist: numpy
Requires-Dist: ipython ; extra == "docs"
Requires-Dist: myst-parser ; extra == "docs"
Requires-Dist: nbsphinx ; extra == "docs"
Requires-Dist: sphinx ; extra == "docs"
Requires-Dist: sphinx-autoapi ; extra == "docs"
Requires-Dist: sphinx-autodoc-typehints ; extra == "docs"
Requires-Dist: sphinx-book-theme ; extra == "docs"
Requires-Dist: coverage ; extra == "test"
Requires-Dist: flit ; extra == "test"
Requires-Dist: ipykernel ; extra == "test"
Requires-Dist: ipython ; extra == "test"
Requires-Dist: ipywidgets ; extra == "test"
Requires-Dist: mypy ; extra == "test"
Requires-Dist: pre-commit ; extra == "test"
Requires-Dist: pytest ; extra == "test"
Requires-Dist: ruff ; extra == "test"
Requires-Dist: twine ; extra == "test"
Requires-Dist: types-requests ; extra == "test"
Project-URL: Documentation, https://github.com/harryhaller001/matplotlib-radar
Project-URL: Homepage, https://github.com/harryhaller001/matplotlib-radar
Project-URL: Source, https://github.com/harryhaller001/matplotlib-radar
Provides-Extra: docs
Provides-Extra: test
